coloripy.py
Coloripy-1.0.4.dist-info/METADATA
Coloripy-1.0.4.dist-info/WHEEL
Coloripy-1.0.4.dist-info/top_level.txt
Coloripy-1.0.4.dist-info/RECORD
