Metadata-Version: 2.1
Name: Coloripy
Version: 1.0.4
Summary: Small module for decorating colors in your script.
Author-email: Pandaxyz-xd <contact@tourble.org>
Project-URL: Homepage, https://github.com/Pandaxyz-xd/Coloripy
Project-URL: Bug Tracker, https://github.com/Pandaxyz-xd/Coloripy/issues
Classifier: Programming Language :: Python :: 3
Classifier: License :: OSI Approved :: MIT License
Classifier: Operating System :: OS Independent
Requires-Python: >=3.7
